LICENSE
MANIFEST.in
README.md
setup.cfg
setup.py
rseng/__init__.py
rseng/version.py
rseng.egg-info/PKG-INFO
rseng.egg-info/SOURCES.txt
rseng.egg-info/dependency_links.txt
rseng.egg-info/entry_points.txt
rseng.egg-info/not-zip-safe
rseng.egg-info/requires.txt
rseng.egg-info/top_level.txt
rseng/client/__init__.py
rseng/client/generate.py
rseng/logger/__init__.py
rseng/logger/message.py
rseng/main/__init__.py
rseng/main/criteria/__init__.py
rseng/main/criteria/criteria-1.0.0.tsv
rseng/main/criteria/criteria-latest.tsv
rseng/main/taxonomy/__init__.py
rseng/main/taxonomy/taxonomy-1.0.0.yaml
rseng/main/taxonomy/taxonomy-latest.yaml
rseng/main/templates/__init__.py
rseng/main/templates/annotate-criteria-template.md
rseng/main/templates/annotate-taxonomy-template.md
rseng/main/templates/criteria-metadata-template.md
rseng/main/templates/taxonomy-metadata-template.md
rseng/utils/__init__.py
rseng/utils/file.py
rseng/utils/prompt.py
tests/__init__.py
tests/test_rseng.py